layerup_security/__init__.py
layerup_security/config.py
layerup_security/layerup_security.py
layerup_security/utils.py
LayerupSecurity-1.3.0.dist-info/LICENSE
LayerupSecurity-1.3.0.dist-info/METADATA
LayerupSecurity-1.3.0.dist-info/WHEEL
LayerupSecurity-1.3.0.dist-info/top_level.txt
LayerupSecurity-1.3.0.dist-info/RECORD
