Metadata-Version: 2.1
Name: LayerupSecurity
Version: 1.3.0
Summary: A Python wrapper for the Layerup Security API.
Home-page: https://github.com/layerupai/layerup-security-sdk-python
Author: Layerup
Author-email: pypi@uselayerup.com
Classifier: Development Status :: 3 - Alpha
Classifier: Intended Audience :: Developers
Classifier: License :: OSI Approved :: MIT License
Classifier: Programming Language :: Python :: 3
Classifier: Programming Language :: Python :: 3.7
Classifier: Programming Language :: Python :: 3.8
Classifier: Programming Language :: Python :: 3.9
Classifier: Programming Language :: Python :: 3.10
Classifier: Topic :: Software Development :: Libraries :: Python Modules
Requires-Python: >=3.7
License-File: LICENSE
Requires-Dist: requests >=2.25.1
